jkq.ddsim-1.10.0.dist-info/LICENSE
jkq.ddsim-1.10.0.dist-info/METADATA
jkq.ddsim-1.10.0.dist-info/top_level.txt
jkq.ddsim-1.10.0.dist-info/RECORD
jkq.ddsim-1.10.0.dist-info/WHEEL
jkq/ddsim/jkqjob.py
jkq/ddsim/unitarysimulator.py
jkq/ddsim/jkqerror.py
jkq/ddsim/statevectorsimulator.py
jkq/ddsim/qasmsimulator.py
jkq/ddsim/jkqprovider.py
jkq/ddsim/hybridstatevectorsimulator.py
jkq/ddsim/pyddsim.cpython-36m-x86_64-linux-gnu.so
jkq/ddsim/__init__.py
jkq/ddsim/hybridqasmsimulator.py
jkq.ddsim.libs/libgomp-a34b3233.so.1.0.0
