Metadata-Version: 2.1
Name: jkq.ddsim
Version: 1.10.0
Summary: JKQ DDSIM - A quantum simulator based on decision diagrams written in C++
Home-page: https://iic.jku.at/eda/research/quantum_simulation/
Author: Stefan Hillmich
Author-email: stefan.hillmich@jku.at
License: MIT
Project-URL: Source, https://github.com/iic-jku/ddsim/
Project-URL: Tracker, https://github.com/iic-jku/ddsim/issues
Project-URL: Research, https://iic.jku.at/eda/research/quantum_simulation/
Keywords: jkq quantum simulation
Platform: UNKNOWN
Classifier: Development Status :: 4 - Beta
Classifier: Programming Language :: Python :: 3
Classifier: Programming Language :: C++
Classifier: License :: OSI Approved :: MIT License
Classifier: Operating System :: Microsoft :: Windows
Classifier: Operating System :: MacOS
Classifier: Operating System :: POSIX :: Linux
Classifier: Intended Audience :: Science/Research
Classifier: Natural Language :: English
Classifier: Topic :: Scientific/Engineering :: Electronic Design Automation (EDA)
License-File: LICENSE
